CHANGES.md
bovine/__init__.py
bovine/activitystreams/__init__.py
bovine/activitystreams/activity_factory.py
bovine/activitystreams/collection_helper.py
bovine/activitystreams/controller.py
bovine/activitystreams/link.py
bovine/activitystreams/media.py
bovine/activitystreams/object_factory.py
bovine/activitystreams/test_activity_factory.py
bovine/activitystreams/test_actor.py
bovine/activitystreams/test_collection_helper.py
bovine/activitystreams/test_controller.py
bovine/activitystreams/test_link.py
bovine/activitystreams/test_media.py
bovine/activitystreams/test_multikey.py
bovine/activitystreams/test_object_factory.py
bovine/activitystreams/test_ordered_collection_builder.py
bovine/activitystreams/test_ordered_collection_page.py
bovine/activitystreams/utils/__init__.py
bovine/activitystreams/utils/print.py
bovine/activitystreams/utils/property_value.py
bovine/activitystreams/utils/test_utils.py
bovine/clients/__init__.py
bovine/clients/authorization_wrapper.py
bovine/clients/bearer.py
bovine/clients/event_source.py
bovine/clients/lookup_account.py
bovine/clients/moo_auth.py
bovine/clients/nodeinfo.py
bovine/clients/signed_http.py
bovine/clients/signed_http_methods.py
bovine/clients/test_bearer.py
bovine/clients/test_event_source.py
bovine/clients/test_lookup_account.py
bovine/clients/test_moo_auth.py
bovine/clients/test_nodeinfo.py
bovine/clients/test_signed_http.py
bovine/clients/test_signed_http_methods.py
bovine/clients/test_utils.py
bovine/clients/utils.py
bovine/clients/web/__init__.py
bovine/clients/web/test_jsonld.py
bovine/crypto/__init__.py
bovine/crypto/digest.py
bovine/crypto/helper.py
bovine/crypto/http_signature.py
bovine/crypto/multibase.py
bovine/crypto/signature.py
bovine/crypto/signature_checker.py
bovine/crypto/test_crypto.py
bovine/crypto/test_digest.py
bovine/crypto/test_helper.py
bovine/crypto/test_http_signature.py
bovine/crypto/test_multibase.py
bovine/crypto/test_signature.py
bovine/crypto/test_signature_checker.py
bovine-0.5.19.dist-info/METADATA
bovine-0.5.19.dist-info/WHEEL
bovine-0.5.19.dist-info/RECORD
