Metadata-Version: 2.1
Name: bovine
Version: 0.5.19
Summary: Core functionality of bovine needed to build fediverse applications
Home-page: https://codeberg.org/bovine/bovine
License: MIT
Keywords: ActivityPub,FediVerse
Author: Helge
Author-email: helge.krueger@gmail.com
Requires-Python: >=3.11,<4.0
Classifier: Intended Audience :: Developers
Classifier: License :: OSI Approved :: MIT License
Classifier: Programming Language :: Python :: 3
Classifier: Programming Language :: Python :: 3.11
Classifier: Programming Language :: Python :: 3.11
Classifier: Programming Language :: Python :: 3.12
Classifier: Topic :: Communications
Classifier: Topic :: Software Development :: Libraries :: Python Modules
Provides-Extra: media
Provides-Extra: repl
Provides-Extra: server
Requires-Dist: aiodns (>=3.0.0,<4.0.0)
Requires-Dist: aiohttp (>=3.8.6,<4.0.0)
Requires-Dist: asyncstdlib (>=3.10.7,<4.0.0)
Requires-Dist: audioread (>=3.0.1,<4.0.0) ; extra == "media"
Requires-Dist: based58 (>=0.1.1,<0.2.0)
Requires-Dist: beautifulsoup4 (>=4.12.2,<5.0.0)
Requires-Dist: black ; extra == "repl"
Requires-Dist: click (>=8.1.7,<9.0.0) ; extra == "repl"
Requires-Dist: cryptography (>=45.0.0,<46.0.0)
Requires-Dist: http-sf (>=1.0.1,<2.0.0)
Requires-Dist: isodate (>=0.7.2,<0.8.0) ; extra == "media"
Requires-Dist: jcs (>=0.2.1,<0.3.0)
Requires-Dist: nh3 (>=0.2.20,<0.3.0) ; extra == "repl"
Requires-Dist: opencv-python (>=4.10.0.84,<5.0.0.0) ; extra == "media"
Requires-Dist: pillow (>=11.0.0,<12.0.0) ; extra == "media"
Requires-Dist: ptpython (>=3.0.23,<4.0.0) ; extra == "repl"
Requires-Dist: pydantic (>=2.5.3,<3.0.0)
Requires-Dist: pyld (>=2.0.3,<3.0.0)
Requires-Dist: quart (>=0.20.0,<0.21.0) ; extra == "server"
Requires-Dist: requests (>=2.30.0,<3.0.0)
Requires-Dist: tomli-w (>=1.1.0,<2.0.0)
Project-URL: Documentation, https://bovine.readthedocs.io/en/latest/
Project-URL: Repository, https://codeberg.org/bovine/bovine
